glue_struct_transform/GlueStructTransform.py
glue_struct_transform/__init__.py
glue_struct_transform/utils.py
glue_struct_transform-0.4.0.dist-info/METADATA
glue_struct_transform-0.4.0.dist-info/WHEEL
glue_struct_transform-0.4.0.dist-info/top_level.txt
glue_struct_transform-0.4.0.dist-info/RECORD
