Metadata-Version: 2.1
Name: glue-struct-transform
Version: 0.4.0
Summary: This libs works to convert a json schema or json to a glue schema struct.
Home-page: https://github.com/VitorArakaki/glue-struct-transform
Author: Vitor Guirardeli Arakaki
Author-email: vi.arakaki@hotmail.com
License: MIT
Platform: UNKNOWN
Classifier: Intended Audience :: Developers
Classifier: License :: OSI Approved :: MIT License
Classifier: Programming Language :: Python
Classifier: Programming Language :: Python :: 3
Classifier: Programming Language :: Python :: 3.6
Classifier: Programming Language :: Python :: 3.7
Classifier: Programming Language :: Python :: 3.8
Classifier: Programming Language :: Python :: 3.9
Classifier: Programming Language :: Python :: 3.10
Classifier: Operating System :: OS Independent
